{
  "common":{
    "chooseImage": "Vui lòng chọn hình ảnh",
    "cancel":"Hủy",
    "saveChange":"Lưu thay đổi",
    "success": "Thành công",
    "error": "Thất bại",
    "notiFailDes": "Có lỗi xảy ra, vui lòng thử lại !",
    "confirm":"Xác nhận",
    "home": "Trang chủ",
    "account": "Tài khoản",
    "promotion": "Khuyến mãi",
    "point": "xu",
    "topUpPoints": "Nạp xu",
    "update": "Cập nhật",
    "push": "Đẩy tin",
    "delete": "Xoá tin",
    "hidden": "Ẩn tin",
    "deleteSuccess": "Xóa thành công!",
    "hiddenSuccess": "Ẩn thành công!",
    "displaySuccess": "Hiện thành công",
    "pushSuccess": "Đẩy tin thành công",
    "all": "Tất cả",
    "New": "Mới",
    "Waitting": "Chờ duyệt",
    "Pending": "Đang xác nhận",
    "Completed": "Đã duyệt",
    "Canceled":"Hủy",
    "errApproved": "Lỗi",
    "noApproved": "Không duyệt",
    "hide": "Ẩn",
    "display": "Hiện",
    "to": "Từ",
    "end": "Tới",
    "action": "Hành động",
    "typeSearch": "Nhập từ khoá muốn tìm",
    "notEnough": "Số dư tài khoản không đủ"
  },
  "valid": {
    "required": "Không được để trống !",
    "requiredPhone": "Số điện thoại không được để trống !",
    "invalidPhone": "Số điện thoại không hợp lệ !",
    "invalidPhoneLong": "Số điện thoại không hợp lệ ( quá dài ) !",
    "invalidPhoneShort": "Số điện thoại không hợp lệ ( quá ngắn ) !",
    "requiredPassword": "Mật khẩu không được để trống !",
    "invalidPassword": "Mật khẩu không hợp lệ !",
    "invalidPasswordLong": "Mật khẩu không hợp lệ ( quá dài )!",
    "invalidPasswordShort": "Mật khẩu không hợp lệ ( quá ngắn )!",
    "retypePassword": "Mật khẩu nhập lại không trùng khớp !",
    "chooseGender": "Vui lòng chọn giới tính !",
    "invalidEmail": "Email không hợp lệ !",
    "selectReal": "Vui lòng chọn tình trạng!",
    "chooseBook": "Vui lòng chọn giấy tờ pháp lý!",
    "videoFail" :"Tệp quá 100MB!",
    "select": "Vui lòng chọn!",
    "priceGTE": "Giá bán phải hơn hơn hoặc bằng 1.000.000 VND"
  },
  "post": {
    "btn": {
      "back": "Quay lại",
      "next": "Tiếp theo",
      "postNow": "Đăng bài ngay",
      "updatePost": "Cập nhật bài đăng",
      "new": "Tin mới"
    },
    "common": {
      "createPublic": "Tạo bài đăng thành công!",
      "createFail": "Tạo bài đăng thất bại!",
      "postManagement": "Quản lý tin đăng",
      "post": "Đăng tin",
      "postRealEstate" : "Đăng tin bất động sản",
      "textPostRealEstate": "Vui lòng nhập đầy đủ thông tin theo mẫu để tối ưu bài đăng của bạn",
      "enterCommission": "Nhập % hoa hồng",
      "commission": "Số hoa hồng",
      "first": "Đầu tiên, xin vui lòng cho chúng tôi biết bạn là",
      "lowPrice": "Giá không được nhỏ hơn {{price}}"
    },
    "title": {
      "confirmPushPost": "Bạn có muốn dùng {{point}} điểm để đẩy tin #{{id}} không ?",
      "contactInformation": "Thông tin liên hệ",
      "postInfo": "Thông tin bài đăng",
      "utilities": "Tiện ích",
      "apartment": "Thông tin căn hộ/ chung cư",
      "moreInformation": "Thông tin thêm",
      "suggestedPrice": "Giá cả gợi ý",
      "areaAndSizeInformation": "Thông tin diện tích, kích thước",
      "priceInformation": "Thông tin giá cả",
      "locationInformation": "Thông tin vị trí",
      "providePicturesAndVideos": "Cung cấp hình ảnh và Video",
      "typeOfApartment": "Chi tiết loại hình bất động sản",
      "typeOfRealEstate": "Loại hình bất động sản",
      "selectThePostingCategory" : "Lựa chọn danh mục đăng tin",
      "start": "Bắt đầu,"
    },
    "postInfo": {
      "title": "Tiêu đề",
      "fillInTheTitle": "Điền tiêu đề để thu hút nhiều lượt xem tin hơn",
      "detailedContentDescription": "Mô tả nội dung chi tiết",
      "introduceTheDetails": "Giới thiệu chi tiết về bất động sản mà bạn đăng tin đầy đủ và rõ ràng, để thu hút thêm người xem",
      "request": "Yêu cầu",
      "doNotWrite": "Không ghi \"Cần bán\"",
      "doNotInclude": "Không chèn giá và số điện thoại ở tiêu đề",
      "description": "Mô tả bằng tiếng Việt có dấu",
      "numberOfFloors": "Số tầng lầu. Số phòng ngủ, phòng khách, bếp, vệ sinh... ",
      "basicFurniture": "Nội thất cơ bản hoặc liệt kê nội thất có sẵn. Thời gian đến các quận trung tâm hay bệnh viện, trường học, siêu thị, chợ gần nhất"
    },
    "contactInformation": {
      "agency": "Môi giới",
      "individual": "Cá nhân",
      "fullName": "Họ tên",
      "mrmrs": "Ông (Bà)",
      "phone": "Số điện thoại liên lạc",
      "clickContact": "Nhấp số điện thoại liên hệ",
      "email": "Email",
      "enterEmail": "Nhập email",
      "address": "Địa chỉ liên hệ",
      "enterAddress": "Nhập địa chỉ",
      "contactType": "Loại liên hệ",
      "selectContactType": "Chọn loại liên hệ",
      "host": "Chủ nhà",
      "allowBrokers": "Cho phép Môi giới"
    },
    "utilities": {
      "loadListFail": "Tải danh sách tiện bị lỗi!"
    },
    "apartment": {
      "real" : "Tình trạng bất động sản",
      "notYet" : "Chưa bàn giao",
      "handed": "Đã bàn giao",
      "sleep": "Số phòng ngủ",
      "restrooms": "Số phòng vệ sinh",
      "kitchen": "Phòng bếp",
      "livingRoom": "Phòng khách",
      "numberOfFloors": "Số tầng",
      "mainDoorDirection": "Hướng cửa chính",
      "chooseTheDirection" : "Chọn hướng cửa chính",
      "balconyDirection" : "Hướng ban công",
      "chooseMainDoor": "Chọn hướng ban công",
      "legalDocuments": "Giấy tờ pháp lý",
      "privatePinkBook": "Sổ hồng riêng",
      "fingerPost": "Giấy viết tay",
      "commonPinkBook":"Sổ hồng chung",
      "notarized": "Công chứng vi bằng",
      "redBook": "Sổ đỏ",
      "noBookYet": "Chưa có sổ",
      "interiorCondition": "Tình trạng nội thất",
      "apartments": "Căn hộ là căn góc",
      "blockTower": "Block/ Tháp",
      "frequency" : "Tầng số",
      "apartmentCode": "Mã căn/ Mã căn hộ",
      "allowApartment": "Cho phép hiển thị mã căn hộ trong tin rao"
    }, 
    "suggestedPrice": {
      "popularText": "Giá bất động sản phổ biến trong cùng 1 khu vực so với mức giá theo bài đăng của bạn. Được cập nhật mới nhất theo công cụ định giá của chúng tôi.",
      "medium": "Trung bình",
      "million": "Triệu/ m2",
      "popularPrice": "Khoảng giá phổ biến Tháng 9/2021",
      "lowestPrice": "Giá thấp nhất theo m2",
      "suggestedPrice": "Giá gợi ý theo m2",
      "highestPrice": "Giá cao nhất theo m2",
      "money": " triệu đồng",
      "yourPrice": "Giá của bạn/ m2",
      "totalPrice": "Giá tổng",
      "successRate": "Tỷ lệ thành công",
      "commentRate":"Tỷ lệ thành công cao vì giá bán của bạn rất thấp so với đề xuất. Lợi nhuận giảm mạnh. Cần điều chỉnh.",
      "lowPrice": "{{price}} triệu đồng. Rất thấp so với giá phổ biến!",
      "minImage": "Vui lòng tải lên tối thiểu 3 hình, tối đa 5 hình"
    },
    "areaAndSizeInformation": {
      "acreage" : "Diện tích",
      "horizontal": "Chiều ngang",
      "longs": "Chiều dài",
      "usableArea": "Diện tích sử dụng",
      "areaOfRecognition": "Diện tích công nhận",
      "roadArea": "Diện tích lộ giới",
      "constructionArea" : "Diện tích xây dựng",
      "landDirection" : "Hướng đất",
      "chooseLand": "Chọn hướng đất",
      "earthShape": "Hình dáng đất",
      "chooseShape": "Chọn hình dáng",
      "price": "Giá",
      "pricem2": "Giá/m2",
      "maximumRental": "Giá thuê/ mua tối đa",
      "deposit": "Tiền cọc",
      "typePrice": "Vui lòng nhập giá hoặc giá/m2"
    },
    "locationInformation": {
      "project": "Tên khu dân cư/ dự án",
      "enterTheName": "Nhập tên khu dân cư",
      "city" : "Tỉnh/ Thành phố",
      "selectCity":"Vui lòng chọn tỉnh, thành phố",
      "district": "Quận/ Huyện",
      "selectDistrict":"Vui lòng chọn khu vực quận, huyện",
      "wards": "Phường/ Xã",
      "selectWards":"Vui lòng chọn xã, phường",
      "apartmentNumber": "Số nhà",
      "enterHouse": "Nhập số nhà",
      "showHouse" : "Hiển thị số nhà trong tin rao",
      "street": "Tên đường",
      "selectStreet":"Vui lòng chọn tên đường"
    },
    "providePicturesAndVideos" : {
      "realEstatePictures": "Hình ảnh Bất động sản",
      "picturesAround": "Hình ảnh xung quanh",
      "clickToUpload": "Nhấp vào để tải lên",
      "picturesInside": "Hình ảnh bên trong",
      "request" : "Yêu cầu cho hình ảnh và video",
      "you" : "Bạn cần đăng ít nhất 3 ảnh ",
      "video" : "Độ dài video không vượt quá 3 phút ",
      "youNeed": "Bạn cần đăng ít nhất 3 ảnh ",
      "limitVideo": "Giới hạn 1 video/tin đăng và 10 tin đăng có video/ tháng",
      "toSell" : "Để bán nhanh hơn",
      "takePictures": "Chụp hình khổ ngang: chính diện, phòng khách, phòng ngủ, bếp, vệ sinh hay ban công của ngôi nhà",
      "no" : "Không",
      "usingDuplicate": "Sử dụng hình ảnh trùng lặp hoặc lấy từ Internet",
      "insertPhone": "Chèn số điện thoại/email/logo vào hình"
    },
    "typeOfApartment": {
      "apartment": "Chung cư",
      "duplex": "Duplex",
      "penhouse": "Penhouse",
      "officietel": "Officietel",
      "serviced": "Căn hộ dịch vụ, mini",
      "dormitories":"Tập thể, cư xá"
    },
    "typeOfRealEstate": {
      "apartment": "Căn hộ/ Chung cư",
      "house": "Nhà ở",
      "land": "Đất/ Dự án",
      "office": "Văn phòng/ Mặt bằng kinh doanh"
    },
    "selectThePostingCategory" : {
      "doYou":"Bạn có nhu cầu đăng tin",
      "buying":"Cần bán bất động sản",
      "real":"Cho thuê bất động sản",
      "project":"Dự án"
    }
  },
  "login": {
    "welcome": "Chào mừng bạn !",
    "pleaseToLogin": "Vui lòng đăng nhập để trải nghiệm tốt hơn",
    "login": "Đăng nhập",
    "signup": "Đăng kí",
    "loginPhoneNumber": "Đăng nhập bằng số điện thoại",
    "orLoginWith": "Hoặc đăng nhập bằng",
    "notAccountYet": "Bạn chưa có tài khoản?",
    "signupNow": "Đăng kí ngay",
    "notiFail": "Đăng nhập thất bại !",
    "notiFailDes": "Tài khoản hoặc mật khẩu không đúng",
    "notiEmailFail": "Gửi email lấy lại mật khẩu thất bại !",
    "forgotPassword":"Quên mật khẩu",
    "typeEmailToGetPassword":"Nhập email để lấy lại mật khẩu",
    "goback":"Quay lại",
    "confirmEmail":"Xác nhận email",
    "successTextEmail":"Link khôi phục mật khẩu đã gửi đến email của bạn, vui lòng kiểm tra và cập nhật mật khẩu mới.",
    "gobackLogin":"Trở về đăng nhập"
  },
  "signup": {
    "welcome": "Xin chào bạn",
    "signupForFree": "Đăng kí hoàn toàn miễn phí",
    "login": "Đăng nhập",
    "signup": "Đăng kí",
    "signupPhoneNumber": "Đăng kí bằng số điện thoại",
    "typePassword": "Tạo 1 mật khẩu ít nhất 6 kí tự",
    "retypePassword": "Nhập lại mật khẩu",
    "orLoginWith": "Hoặc đăng nhập bằng",
    "haveAnAccount": "Bạn đã có tài khoản?",
    "loginNow": "Đăng nhập ngay",
    "notiFail": "Đăng kí thất bại"
  },
  "otpForm": {
    "confirmOtp": "Xác nhận OTP",
    "otpSendTo": "OTP đã được gửi đến ",
    "otpWrongText": "Mã OTP sai, vui lòng thử lại",
    "resendOtp": "Gửi mã OTP mới",
    "confirmSignup": "Xác nhận đăng kí",
    "notiSuccess": "Đăng kí thành công",
    "notiFail": "Đăng kí thất bại",
    "notiFailDes": "Số điện thoại đã được dùng"
  },
  "sliderMenu":{
    "home":"Trang chủ",
    "managePost":"Quản lý tin đăng",
    "post":"Đăng tin",
    "postForAgency":"Đăng tin dành cho môi giới",
    "postOfSell":"Xem tin bán và cho thuê",
    "listOfPost":"Danh sách tin đã quan tâm",
    "manageTransaction":"Quản lý giao dịch",
    "accountBalance":"Số dư tài khoản",
    "transactionHistory":"Lịch sử giao dịch",
    "manageAcc":"Quản lý tài khoản",
    "accInfor":"Thông tin cá nhân",
    "verifyAccount":"Xác thực tài khoản",
    "changePassword":"Đổi mật khẩu",
    "logOut":"Đăng xuất",
    "paymentRecord": "Lịch sử thanh toán bài đăng"
  },
  "AccountVerification":{
    "accountVerification": "Xác thực tài khoản",
    "choicePackage":"Vui lòng chọn gói nạp và phương thức thanh toán",
    "identityNumber": "CMND/ Thẻ căn cước/ Passport",
    "frontImage": "Ảnh mặt trước",
    "backImage": "Ảnh mặt sau",
    "uploadIns": "Nhấp vào vị trí này để tải lên",
    "notiUpFrontSuccess":"Tải ảnh mặt trước thành công",
    "notiUpFrontFail":"Tải ảnh mặt trước thất bại",
    "notiUpBackSuccess":"Tải ảnh mặt sau thành công",
    "notiUpBackFail":"Tải ảnh mặt sau thất bại",
    "notiUpload": "Vui lòng tải lên ảnh CMND",
    "notiSuccess":"Tải thông tin xác thực thành công !",
    "notiFail":"Tải thông tin xác thực thất bại !",
    "notiFailDes":"Có lỗi xảy ra, vui lòng thử lại !",
    "breadcrumbFirst":"Trang chủ",
    "breadcrumbSecond":"Quản lý tài khoản",
    "breadcrumbThird":"Xác thực tài khoản",
    "emailIsUsed": "Email đã được sử dụng"
  },
  "AccountInformation":{
    "accountInformation":"Thông tin cá nhân",
    "fullName":"Họ và tên",
    "phoneNumber":"Số điện thoại",
    "dateOfBirth":"Ngày sinh",
    "sex":"Giới tính",
    "male":"Nam",
    "female":"Nữ",
    "im":"Tôi là",
    "individual":"Cá nhân",
    "agency":"Môi giới",
    "emailUnconfirm":"Email của bạn chưa được xác nhận, vui lòng kiểm tra hộp thư đến của bạn",
    "notiSuccess":"Cập nhật thông tin cá nhân thành công!",
    "notiFail":"Cập nhật thông tin cá nhân thất bại!",
    "notiFailDes":"Có lỗi xảy ra, vui lòng thử lại sau ",
    "notiSuccessEmail":"Đã gửi mail xác thực vào ",
    "notiSuccessEmailDes":"Vui lòng kiểm tra email !",
    "notiFailEmail":"Gửi mail xác thực thất bại",
    "resendEmail":"Gửi lại",
    "breadcrumbFist":"Trang chủ",
    "breadcrumbSecond":"Quản lý tài khoản",
    "breadcrumbThird":"Thông tin cá nhân",
    "notiFailPhoneNumber":"Số điện thoại đã được sử dụng",
    "verifyCodeHasSend":"Một mã xác thực đã được gửi đến số",
    "address": "Địa chỉ",
    "city" : "Tỉnh/ Thành phố",
    "district": "Quận/ Huyện",
    "wards": "Phường/ Xã",
    "selectCity":"Vui lòng chọn tỉnh, thành phố",
    "selectDistrict":"Vui lòng chọn khu vực quận, huyện",
    "selectWards":"Vui lòng chọn xã, phường",
    "verifiedInfo": "Tài khoản của bạn đã được xác thực!",
    "deleteImg": "Xoá ảnh"
  },
  "RealEstateUserSaved":{
    "all":"Tất cả",
    "postType":"Loại hình",
    "approveStatus":"Tình trạng",
    "buysell":"Cần bán",
    "rental":"Cho thuê",
    "project":"Dự án",
    "individual":"Cá nhân",
    "agency":"Môi giới",
    "reject":"Từ chối",
    "notCYet":"Chưa duyệt",
    "didC":"Đã duyệt",
    "addFilter":"Lọc thêm",
    "realEstateId":"Mã tin",
    "realEstateTitle":"Tiêu đề",
    "realEstatePhone":"Số ĐT",
    "realEstateContactTypeId":"Người đăng",
    "createdAt":"Ngày đăng",
    "realEstateValueSalePrice":"Giá",
    "realEstatePostTypeId":"Loại hình",
    "notiFail":"Tải danh sách tin quan tâm thất bại",
    "notiFailDes":"Vui lòng thử lại sau !",
    "unitb":"tỷ",
    "breadcrumbFirst":"Trang chủ",
    "breadcrumbSecond":"Quản lý tin đăng",
    "breadcrumbThird":"Danh sách tin đã quan tâm",
    "clickToSort":"Nhấp vào để sắp xếp",
    "see":"Xem",
    "infor":"Thông tin",
    "of":"của",
    "items":"tin",
    "status": "Trạng thái"
  },
  "pageHeaderUser":{
    "personInfor":"Thông tin cá nhân",
    "helloIm":"Xin chào, Tôi tên là",
    "notiSuccess":"Cập nhật ảnh đại diện thành công !",
    "notiFail":"Cập nhật ảnh đại diện thất bại !",
    "host":"Chủ nhà",
    "changeAvatar":"Thay đổi ảnh đại diện",
    "accVerified":"Tài khoản đã xác minh",
    "accUnverified":"Tài khoản chưa xác minh",
    "identity":"Danh tính",
    "phoneNumber":"Số điện thoại"
  },
  "changePassword":{
    "changPassword":"Đổi mật khẩu",
    "notiSuccess":"Đổi mật khẩu thành công!",
    "notiFail":"Đổi mật khẩu thất bại !",
    "notiFailDes":"Mật khẩu hiện tại không chính xác!",
    "breadcrumbFirst":"Trang chủ",
    "breadcrumbSecond":"Quản lý tài khoản",
    "breadcrumbThird":"Đổi mật khẩu",
    "currentPassword":"Mật khẩu hiện tại",
    "newPassword":"Mật khẩu mới",
    "retypeNewPassword":"Xác nhận mật khẩu"
  },
  "loginGgVsFb": {
    "notiGGFail":"Đăng nhập bằng Google thất bại!",
    "notiFBFail":"Đăng nhập bằng Facebook thất bại!"
  },
  "viewNewsForSaleAndRent": "Xem tin bán và cho thuê",
  "transactionHistory": {
    "index" : "Mã tin",
    "state": "Trạng thái",
    "depositAmount": "Số tiền nạp",
    "date": "Thời gian",
    "payment": "Phương thức thanh toán",
    "points": "Số điểm quy đổi",
    "trading": "Mã giao dịch"
  },
  "resetPassword": {
    "resetPassword": "Khôi phục mật khẩu",
    "passwordsDontMatch": "Hai mật khẩu bạn đã nhập không khớp!",
    "typePassword": "Nhập mật khẩu mới",
    "typeCfPassword": "Xác nhận mật khẩu mới",
    "resetSuccess": "Khôi phục mật khẩu thành công!",
    "resetSuccessSubtitle": "Bạn đã có thể truy cập vào tài khoản.",
    "resetFailed": "Khôi phục mật khẩu thất bại!",
    "resetFailedSubtitle": "Có vẻ điều gì đó đang hoạt động không đúng.",
    "errorSection": "Nội dung bạn gửi có lỗi sau:",
    "invalidAccount": "Tài khoản của bạn đã bị khoá.",
    "invalidToken": "Token đã hết hạn."
  },
  "accountBalance": {
    "choosePackage": "Lựa chọn gói nạp",
    "viewHistory": "Xem lịch sử giao dịch",
    "packageInfo": "Thông tin gói nạp xu",
    "pointReward": "Xu quy đổi",
    "pay": "Thanh toán",
    "pack": "Gói",
    "paynow": "Thanh toán ngay",
    "agreeService": "Tôi đồng ý",
    "service": "Điều khoản sử dụng",
    "backToInfo": "Trở lại trang thông tin",
    "confirmSuccess": "Xác nhận email thành công!<br/>Tài khoản của bạn đã xác nhận email.",
    "confirmFailed": "Xác nhận email thất bại!<br/>Có vẻ điều gì đó đã sai sót. Vui lòng thử gửi email xác nhận khác.",
    "agreeRule": "Bạn phải đồng ý các điều khoản để thực hiện giao dịch"
  },
  "PaymentRecord": {
    "paymentTargetId":"Mã tin",
    "paymentTargetName":"Bài đăng",
    "walletId":"Ví",
    "paymentTargetType":"Mục đích",
    "breadcrumbFirst":"Trang chủ",
    "breadcrumbSecond":"Quản lý giao dịch",
    "breadcrumbThird":"Lịch sử thanh toán bài đăng",
    "notiFail":"Lấy dữ liệu thất bại",
    "notiFailDes":"Có lỗi xảy ra, vui lòng thử lại !",
    "createdAt":"Ngày thanh toán",
    "paymentAmount":"Số xu",
    "payment":"trạng thái thanh toán",
    "of":"của",
    "items":"tin",
    "clickToSort":"Nhấp vào để sắp xếp"
  },
  "PaymentPage": {
    "complete":"Hoàn tất",
    "status":"Trạng thái thanh toán",
    "amount":"Số tiền",
    "transactionId":"Mã giao dịch",
    "transFail":"Thanh toán thất bại",
    "createdAt":"Thời gian",
    "notiFail":"Lấy dữ liệu thất bại",
    "notiFailDes":"Có lỗi xảy ra, vui lòng thử lại !",
    "paymentTransactionPage":"Thông tin thanh toán"
  }
}